Workbook

Sheet Resumen
A1: Caso de negocio: resumen ejecutivo
A3: Indicador | B3: Conservador | C3: Base | D3: Optimista
A4: Multiplicador de beneficios | B4: =Supuestos!$B$26 | C4: =Supuestos!$B$27 | D4: =Supuestos!$B$28
A5: Beneficio anual (anio 2) | B5: =Supuestos!$B$10*B4 | C5: =Supuestos!$B$10*C4 | D5: =Supuestos!$B$10*D4
A6: VAN | B6: =Flujos_Conservador!B14 | C6: =Flujos_Base!B14 | D6: =Flujos_Optimista!B14
A7: TIR | B7: =Flujos_Conservador!B15 | C7: =Flujos_Base!B15 | D7: =Flujos_Optimista!B15
A8: Payback (anios) | B8: =Flujos_Conservador!B16 | C8: =Flujos_Base!B16 | D8: =Flujos_Optimista!B16
A10: Beneficio anual base en la cadena | B10: =Supuestos!$B$10
A11: Inversion inicial + capital de trabajo | B11: =Supuestos!$B$13+Supuestos!$B$12
A12: Factor de validacion del piloto | B12: =Supuestos!$B$9

Sheet Supuestos
A1: Caso de negocio: supuestos
A3: Pares en la simulacion | B3: 240
A4: Pares en la cadena | B4: 3920
A5: Factor de escala | B5: =B4/B3
A6: Ahorro anual simulado (240 pares) | B6: 209435.05
A7: Efecto fill simulado (pp) | B7: 2.5843197
A8: Efecto fill piloto (pp) | B8: 2.2381377
A9: Factor de validacion del piloto | B9: =MIN(1,B8/B7)
A10: Ahorro anual base en la cadena | B10: =B5*B6*B9
A11: Capital de trabajo adicional (muestra) | B11: 8096.5076
A12: Capital de trabajo adicional (cadena) | B12: =B11*B5
A13: Inversion inicial | B13: =B14+B15
A14: Implementacion | B14: 380000
A15: Cambio de procesos | B15: 120000
A16: Costo de operacion anual | B16: 96000
A17: Tasa de impuesto | B17: 0.27
A18: Tasa de descuento | B18: 0.12
A19: Anios | B19: 3
A20: Depreciacion anual | B20: =B13/B19
A21: Ramp-up anio 1 | B21: 0.8
A22: Ramp-up anio 2 | B22: 1
A23: Ramp-up anio 3 | B23: 1
A25: Escenarios
A26: Conservador | B26: 0.6
A27: Base | B27: 1
A28: Optimista | B28: 1.4
A30: Beneficios por componente (UM anuales en la cadena)
A31: Costo de orden | B31: 1619832.8
A32: Costo de quiebre | B32: 564389.13
A33: Costo de merma | B33: 800082.11
A34: Costo de almacenamiento | B34: -21760.39
A35: Total | B35: =SUM(B31:B34)

Sheet Beneficios
A1: Beneficios anuales por componente
A3: Componente | B3: Muestra | C3: Factor escala | D3: Validacion piloto | E3: Cadena
A4: Costo de orden | B4: 114513 | C4: =Supuestos!$B$5 | D4: =Supuestos!$B$9 | E4: =B4*C4*D4
A5: Costo de quiebre | B5: 39899.11 | C5: =Supuestos!$B$5 | D5: =Supuestos!$B$9 | E5: =B5*C5*D5
A6: Costo de merma | B6: 56561.27 | C6: =Supuestos!$B$5 | D6: =Supuestos!$B$9 | E6: =B6*C6*D6
A7: Costo de almacenamiento | B7: -1538.34 | C7: =Supuestos!$B$5 | D7: =Supuestos!$B$9 | E7: =B7*C7*D7
A8: Total | E8: =SUM(E4:E7)

Sheet Flujos_Conservador
A1: Flujos de caja - escenario conservador
A2: Multiplicador de beneficios | B2: =Supuestos!$B$26
B3: Anio 0 | C3: Anio 1 | D3: Anio 2 | E3: Anio 3
A4: Beneficio | B4: 0 | C4: =Supuestos!$B$10*$B$2*Supuestos!$B$21 | D4: =Supuestos!$B$10*$B$2*Supuestos!$B$22 | E4: =Supuestos!$B$10*$B$2*Supuestos!$B$23
A5: Costo de operacion | B5: 0 | C5: =-Supuestos!$B$16 | D5: =-Supuestos!$B$16 | E5: =-Supuestos!$B$16
A6: Depreciacion | B6: 0 | C6: =-Supuestos!$B$20 | D6: =-Supuestos!$B$20 | E6: =-Supuestos!$B$20
A7: EBIT | B7: =SUM(B4:B6) | C7: =SUM(C4:C6) | D7: =SUM(D4:D6) | E7: =SUM(E4:E6)
A8: Impuesto | B8: =-MAX(0,B7)*Supuestos!$B$17 | C8: =-MAX(0,C7)*Supuestos!$B$17 | D8: =-MAX(0,D7)*Supuestos!$B$17 | E8: =-MAX(0,E7)*Supuestos!$B$17
A9: Flujo operativo | B9: =B7+B8-B6 | C9: =C7+C8-C6 | D9: =D7+D8-D6 | E9: =E7+E8-E6
A10: Inversion inicial | B10: =-Supuestos!$B$13 | C10: 0 | D10: 0 | E10: 0
A11: Capital de trabajo | B11: =-Supuestos!$B$12 | C11: 0 | D11: 0 | E11: =Supuestos!$B$12
A12: Flujo neto | B12: =SUM(B9:B11) | C12: =SUM(C9:C11) | D12: =SUM(D9:D11) | E12: =SUM(E9:E11)
A14: VAN | B14: =NPV(Supuestos!$B$18,C12:E12)+B12
A15: TIR | B15: =IRR(B12:E12)
A16: Payback (anios) | B16: =IF(B12>=0,0,IF(C12>=0,1-B12/C12,IF(D12>=0,2-(B12+C12)/D12,IF(E12>=0,3-(B12+C12+D12)/E12,">3"))))

Sheet Flujos_Base
A1: Flujos de caja - escenario base
A2: Multiplicador de beneficios | B2: =Supuestos!$B$27
B3: Anio 0 | C3: Anio 1 | D3: Anio 2 | E3: Anio 3
A4: Beneficio | B4: 0 | C4: =Supuestos!$B$10*$B$2*Supuestos!$B$21 | D4: =Supuestos!$B$10*$B$2*Supuestos!$B$22 | E4: =Supuestos!$B$10*$B$2*Supuestos!$B$23
A5: Costo de operacion | B5: 0 | C5: =-Supuestos!$B$16 | D5: =-Supuestos!$B$16 | E5: =-Supuestos!$B$16
A6: Depreciacion | B6: 0 | C6: =-Supuestos!$B$20 | D6: =-Supuestos!$B$20 | E6: =-Supuestos!$B$20
A7: EBIT | B7: =SUM(B4:B6) | C7: =SUM(C4:C6) | D7: =SUM(D4:D6) | E7: =SUM(E4:E6)
A8: Impuesto | B8: =-MAX(0,B7)*Supuestos!$B$17 | C8: =-MAX(0,C7)*Supuestos!$B$17 | D8: =-MAX(0,D7)*Supuestos!$B$17 | E8: =-MAX(0,E7)*Supuestos!$B$17
A9: Flujo operativo | B9: =B7+B8-B6 | C9: =C7+C8-C6 | D9: =D7+D8-D6 | E9: =E7+E8-E6
A10: Inversion inicial | B10: =-Supuestos!$B$13 | C10: 0 | D10: 0 | E10: 0
A11: Capital de trabajo | B11: =-Supuestos!$B$12 | C11: 0 | D11: 0 | E11: =Supuestos!$B$12
A12: Flujo neto | B12: =SUM(B9:B11) | C12: =SUM(C9:C11) | D12: =SUM(D9:D11) | E12: =SUM(E9:E11)
A14: VAN | B14: =NPV(Supuestos!$B$18,C12:E12)+B12
A15: TIR | B15: =IRR(B12:E12)
A16: Payback (anios) | B16: =IF(B12>=0,0,IF(C12>=0,1-B12/C12,IF(D12>=0,2-(B12+C12)/D12,IF(E12>=0,3-(B12+C12+D12)/E12,">3"))))

Sheet Flujos_Optimista
A1: Flujos de caja - escenario optimista
A2: Multiplicador de beneficios | B2: =Supuestos!$B$28
B3: Anio 0 | C3: Anio 1 | D3: Anio 2 | E3: Anio 3
A4: Beneficio | B4: 0 | C4: =Supuestos!$B$10*$B$2*Supuestos!$B$21 | D4: =Supuestos!$B$10*$B$2*Supuestos!$B$22 | E4: =Supuestos!$B$10*$B$2*Supuestos!$B$23
A5: Costo de operacion | B5: 0 | C5: =-Supuestos!$B$16 | D5: =-Supuestos!$B$16 | E5: =-Supuestos!$B$16
A6: Depreciacion | B6: 0 | C6: =-Supuestos!$B$20 | D6: =-Supuestos!$B$20 | E6: =-Supuestos!$B$20
A7: EBIT | B7: =SUM(B4:B6) | C7: =SUM(C4:C6) | D7: =SUM(D4:D6) | E7: =SUM(E4:E6)
A8: Impuesto | B8: =-MAX(0,B7)*Supuestos!$B$17 | C8: =-MAX(0,C7)*Supuestos!$B$17 | D8: =-MAX(0,D7)*Supuestos!$B$17 | E8: =-MAX(0,E7)*Supuestos!$B$17
A9: Flujo operativo | B9: =B7+B8-B6 | C9: =C7+C8-C6 | D9: =D7+D8-D6 | E9: =E7+E8-E6
A10: Inversion inicial | B10: =-Supuestos!$B$13 | C10: 0 | D10: 0 | E10: 0
A11: Capital de trabajo | B11: =-Supuestos!$B$12 | C11: 0 | D11: 0 | E11: =Supuestos!$B$12
A12: Flujo neto | B12: =SUM(B9:B11) | C12: =SUM(C9:C11) | D12: =SUM(D9:D11) | E12: =SUM(E9:E11)
A14: VAN | B14: =NPV(Supuestos!$B$18,C12:E12)+B12
A15: TIR | B15: =IRR(B12:E12)
A16: Payback (anios) | B16: =IF(B12>=0,0,IF(C12>=0,1-B12/C12,IF(D12>=0,2-(B12+C12)/D12,IF(E12>=0,3-(B12+C12+D12)/E12,">3"))))
